adbutils_async/__init__.py
adbutils_async/__main__.py
adbutils_async/_adb.py
adbutils_async/_device.py
adbutils_async/_proto.py
adbutils_async/_utils.py
adbutils_async/_version.py
adbutils_async/errors.py
adbutils_async/pidcat.py
adbutils_async/binaries/README.md
adbutils_async/binaries/__init__.py
adbutils_async-0.0.5.dist-info/AUTHORS
adbutils_async-0.0.5.dist-info/LICENSE
adbutils_async-0.0.5.dist-info/METADATA
adbutils_async-0.0.5.dist-info/WHEEL
adbutils_async-0.0.5.dist-info/pbr.json
adbutils_async-0.0.5.dist-info/top_level.txt
adbutils_async-0.0.5.dist-info/RECORD
