Metadata-Version: 2.1
Name: adbutils_async
Version: 0.0.5
Summary: Python adb async library for adb service.
Home-page: https://github.com/touxiaoling/adbutils_async
Author: tomin
Author-email: tomin <tomin@tomin.com>
License: MIT License
Project-URL: homepage, https://github.com/touxiaoling/adbutils_async
Project-URL: repository, https://github.com/touxiaoling/adbutils_async
Project-URL: documentation, https://github.com/touxiaoling/adbutils_async
Keywords: adb,adbutils,async
Classifier: License :: OSI Approved :: MIT License
Classifier: Operating System :: OS Independent
Classifier: Programming Language :: Python :: 3
Classifier: Programming Language :: Python :: 3.10
Classifier: Programming Language :: Python :: 3.11
Classifier: Programming Language :: Python :: 3.12
Requires-Python: >=3.10
License-File: LICENSE
License-File: AUTHORS
Requires-Dist: httpx
Requires-Dist: Pillow
Requires-Dist: deprecation
Requires-Dist: retry
Requires-Dist: apkutils2
